{
  "moduleName": "Mining",
  "data": {
    "items": [
      {
        "id": "LowSpiritMine",
        "name": "灵晶石",
        "desc": "一种很常见的晶石，灵气和纯度较低",
        "media": "LowSpiritMine",
        "price": 5
      },
      {
        "id": "FiveElementsStone",
        "name": "五行晶石",
        "desc": "蕴含金木水火土五种属性的晶石",
        "media": "FiveElementsStone",
        "price": 25
      },
      {
        "id": "MetalStone",
        "name": "金晶石",
        "desc": "蕴含金属性的晶石",
        "media": "MetalStone",
        "price": 5
      },
      {
        "id": "WoodStone",
        "name": "木晶石",
        "desc": "蕴含木属性的晶石",
        "media": "WoodStone",
        "price": 5
      },
      {
        "id": "WaterStone",
        "name": "水晶石",
        "desc": "蕴含水属性的晶石",
        "media": "WaterStone",
        "price": 5
      },
      {
        "id": "FireStone",
        "name": "火晶石",
        "desc": "蕴含火属性的晶石",
        "media": "FireStone",
        "price": 5
      },
      {
        "id": "EarthStone",
        "name": "土晶石",
        "desc": "蕴含土属性的晶石",
        "media": "EarthStone",
        "price": 5
      }
    ],
    "recipes": [
      {
        "id": "Mining:Recipe:LowSpiritMine",
        "name": "采集：灵晶石",
        "desc": "",
        "media": "",
        "interval": 2000,
        "unlockLevel": 1,
        "rewardExperience": 5,
        "rewardItems": [{ "itemId": "LowSpiritMine", "itemQuantity": 1 }]
      },
      {
        "id": "Mining:Recipe:FiveElementsStone",
        "name": "采集：五行晶石",
        "desc": "采集五行晶石，有概率采集到伴生的五种属性的晶石",
        "media": "",
        "interval": 5000,
        "unlockLevel": 1,
        "rewardExperience": 50,
        "rewardItems": [{ "itemId": "FiveElementsStone", "itemQuantity": 1 }],
        "randomRewardItems": [
          { "probability": 10, "itemId": "MetalStone", "itemQuantity": 1 },
          { "probability": 10, "itemId": "WoodStone", "itemQuantity": 1 },
          { "probability": 10, "itemId": "WaterStone", "itemQuantity": 1 },
          { "probability": 10, "itemId": "FireStone", "itemQuantity": 1 },
          { "probability": 10, "itemId": "EarthStone", "itemQuantity": 1 }
        ]
      }
    ]
  }
}
